research_utils_pkg/__init__.py
research_utils_pkg/tools.py
research_utils_pkg-0.0.1.dist-info/LICENSE
research_utils_pkg-0.0.1.dist-info/METADATA
research_utils_pkg-0.0.1.dist-info/WHEEL
research_utils_pkg-0.0.1.dist-info/top_level.txt
research_utils_pkg-0.0.1.dist-info/RECORD
