Metadata-Version: 2.1
Name: research_utils_pkg
Version: 0.0.1
Summary: useful tools I used in coding.
Home-page: https://github.com/876720687/research_utils_pkg
Author: leoye
Author-email: 876720687@qq.com
Classifier: Programming Language :: Python :: 3
Classifier: License :: OSI Approved :: Apache Software License
Classifier: Operating System :: OS Independent
Requires-Python: >=3.6
License-File: LICENSE
